injex/__init__.py
injex-1.0.0.dist-info/LICENSE
injex-1.0.0.dist-info/METADATA
injex-1.0.0.dist-info/WHEEL
injex-1.0.0.dist-info/top_level.txt
injex-1.0.0.dist-info/RECORD
