Metadata-Version: 2.1
Name: injex
Version: 1.0.0
Summary: DI container for Python applications
Author-email: vshulcz <vshulcz@gmail.com>
Project-URL: Homepage, https://github.com/vshulcz/injex
Keywords: dependency,injection,di,container,ddd
Classifier: Development Status :: 5 - Production/Stable
Classifier: License :: OSI Approved :: MIT License
Classifier: Programming Language :: Python :: 3
Classifier: Programming Language :: Python :: 3.10
Classifier: Programming Language :: Python :: 3.11
Classifier: Programming Language :: Python :: 3.12
Classifier: Programming Language :: Python :: 3.13
Classifier: Operating System :: OS Independent
Requires-Python: >=3.10
License-File: LICENSE
